configuris/__init__.py
configuris/_exceptions.py
configuris-0.1.0.dist-info/LICENSE
configuris-0.1.0.dist-info/METADATA
configuris-0.1.0.dist-info/WHEEL
configuris-0.1.0.dist-info/top_level.txt
configuris-0.1.0.dist-info/RECORD
