Metadata-Version: 2.1
Name: configuris
Version: 0.1.0
Summary: Configuration management made easy
Home-page: https://github.com/n1clud3/configuris
Author: n1clud3
Author-email: n1clud3@proton.me
Project-URL: Bug Tracker, https://github.com/n1clud3/configuris/issues
Classifier: Programming Language :: Python :: 3
Classifier: License :: OSI Approved :: MIT License
Classifier: Operating System :: OS Independent
Requires-Python: >=3.6
License-File: LICENSE
